msgpack/__init__.py
msgpack/exceptions.py
msgpack/fallback.py
msgpack/ext.py
msgpack/_cmsgpack.cpython-313-darwin.so
msgpack-1.1.1.dist-info/RECORD
msgpack-1.1.1.dist-info/WHEEL
msgpack-1.1.1.dist-info/top_level.txt
msgpack-1.1.1.dist-info/METADATA
msgpack-1.1.1.dist-info/licenses/COPYING
