Metadata-Version: 2.1
Name: msgpack
Version: 1.1.1
Summary: MessagePack serializer
Author-email: Inada Naoki <songofacandy@gmail.com>
License: Apache 2.0
Project-URL: Homepage, https://msgpack.org/
Project-URL: Documentation, https://msgpack-python.readthedocs.io/
Project-URL: Repository, https://github.com/msgpack/msgpack-python/
Project-URL: Tracker, https://github.com/msgpack/msgpack-python/issues
Project-URL: Changelog, https://github.com/msgpack/msgpack-python/blob/main/ChangeLog.rst
Keywords: msgpack,messagepack,serializer,serialization,binary
Classifier: Development Status :: 5 - Production/Stable
Classifier: Operating System :: OS Independent
Classifier: Topic :: File Formats
Classifier: Intended Audience :: Developers
Classifier: Programming Language :: Python :: 3.8
Classifier: Programming Language :: Python :: 3.9
Classifier: Programming Language :: Python :: 3.10
Classifier: Programming Language :: Python :: 3.11
Classifier: Programming Language :: Python :: 3.12
Classifier: Programming Language :: Python :: 3.13
Classifier: Programming Language :: Python :: 3.14
Classifier: Programming Language :: Python :: Implementation :: CPython
Classifier: Programming Language :: Python :: Implementation :: PyPy
Requires-Python: >=3.8
License-File: COPYING
